steel_seal/__init__.py
steel_seal/signature.py
steel_seal/engine/__init__.py
steel_seal/engine/engine.py
steel_seal/engine/memory.py
steel_seal/engine/redis.py
steel_seal/util/__init__.py
steel_seal/util/util.py
steel_seal-0.0.4.dist-info/LICENSE
steel_seal-0.0.4.dist-info/METADATA
steel_seal-0.0.4.dist-info/WHEEL
steel_seal-0.0.4.dist-info/top_level.txt
steel_seal-0.0.4.dist-info/RECORD
