Metadata-Version: 2.1
Name: steel-seal
Version: 0.0.4
Summary: 简单、易用且支持防重放的签名工具
Home-page: UNKNOWN
Author: afeyer
Author-email: afeyer@h5base.cn
License: UNKNOWN
Platform: UNKNOWN
Requires-Python: >=3.0
License-File: LICENSE
Requires-Dist: pydantic
